pyteseo/__init__.py
pyteseo/classes.py
pyteseo/defaults.py
pyteseo/wrapper.py
pyteseo/data/substances/hns.xlsx
pyteseo/data/substances/hns_units.xlsx
pyteseo/data/substances/oil.xlsx
pyteseo/data/substances/oil_units.xlsx
pyteseo/export/__init__.py
pyteseo/export/grids.py
pyteseo/export/particles.py
pyteseo/export/properties.py
pyteseo/io/__init__.py
pyteseo/io/cfg.py
pyteseo/io/coastline.py
pyteseo/io/forcings.py
pyteseo/io/grid.py
pyteseo/io/hns_calib.py
pyteseo/io/results.py
pyteseo/io/run.py
pyteseo/io/substances.py
pyteseo/io/utils.py
pyteseo/plot/__init__.py
pyteseo/plot/animations.py
pyteseo/plot/basics.py
pyteseo/plot/figures.py
pyteseo/preprocess/__init__.py
pyteseo/preprocess/dataset.py
pyteseo/preprocess/geodataframe.py
pyteseo/preprocess/teseo_domain.py
pyteseo/preprocess/teseo_forcing.py
pyteseo/preprocess/teseo_standarizations.py
pyteseo/providers/__init__.py
pyteseo/providers/cmems.py
pyteseo/providers/connection.py
pyteseo/providers/emodnet.py
pyteseo/providers/ihcantabria.py
pyteseo/providers/noaa.py
pyteseo/providers/providers_registry.json
pyteseo/tests/__init__.py
pyteseo/tests/data/cas1_grid_001_000000.txt
pyteseo/tests/data/cas1_grid_001_000005.txt
pyteseo/tests/data/cas1_grid_001_000010.txt
pyteseo/tests/data/cas1_grid_001_000015.txt
pyteseo/tests/data/cas1_grid_001_000020.txt
pyteseo/tests/data/cas1_grid_001_000025.txt
pyteseo/tests/data/cas1_grid_001_000030.txt
pyteseo/tests/data/cas1_grid_001_000035.txt
pyteseo/tests/data/cas1_grid_001_000040.txt
pyteseo/tests/data/cas1_grid_001_000045.txt
pyteseo/tests/data/cas1_grid_001_000050.txt
pyteseo/tests/data/cas1_grid_001_000055.txt
pyteseo/tests/data/cas1_grid_001_000060.txt
pyteseo/tests/data/cas1_grid_001_000065.txt
pyteseo/tests/data/cas1_grid_001_000070.txt
pyteseo/tests/data/cas1_grid_001_000075.txt
pyteseo/tests/data/cas1_grid_001_000080.txt
pyteseo/tests/data/cas1_grid_001_000085.txt
pyteseo/tests/data/cas1_grid_001_000090.txt
pyteseo/tests/data/cas1_grid_002_000000.txt
pyteseo-0.0.7.dist-info/entry_points.txt
pyteseo-0.0.7.dist-info/LICENSE.md
pyteseo-0.0.7.dist-info/WHEEL
pyteseo-0.0.7.dist-info/METADATA
pyteseo-0.0.7.dist-info/RECORD
