Metadata-Version: 2.1
Name: pyteseo
Version: 0.0.7
Summary: Python package developed to simplify and facilitate the setup and postprocessing of TESEO(v1.2.8) simulations (https://ihcantabria.com/en/specialized-software/teseo/)
Author-email: German Aragon Caminero <german.aragon@unican.es>
Requires-Python: >=3.8
Classifier: Topic :: Scientific/Engineering
Classifier: Topic :: Scientific/Engineering :: Physics
Classifier: Development Status :: 1 - Planning
Classifier: Programming Language :: Python
Classifier: Programming Language :: Python
Classifier: Programming Language :: Python :: 3
Classifier: Programming Language :: Python :: 3 :: Only
Classifier: Programming Language :: Python :: 3.8
Classifier: Programming Language :: Python :: 3.9
Classifier: Programming Language :: Python :: 3.10
Classifier: Programming Language :: Python :: 3.11
Requires-Dist: geopandas
Requires-Dist: owslib
Requires-Dist: xarray
Requires-Dist: dask
Requires-Dist: netcdf4
Requires-Dist: bottleneck
Requires-Dist: ipykernel
Requires-Dist: matplotlib
Requires-Dist: geojson
Requires-Dist: pytest >=7
Requires-Dist: lxml
Requires-Dist: scipy
Requires-Dist: python-dotenv
Requires-Dist: pydap
Requires-Dist: openpyxl
Requires-Dist: flit ; extra == "dev"
Requires-Dist: black ; extra == "dev"
Requires-Dist: sphinx ; extra == "dev"
Requires-Dist: coverage[toml] ; extra == "dev"
Requires-Dist: myst-nb ; extra == "dev"
Requires-Dist: sphinx-autoapi ; extra == "dev"
Requires-Dist: sphinx_rtd_theme ; extra == "dev"
Project-URL: changelog, https://github.com/IHCantabria/pyteseo/blob/main/CHANGELOG.md
Project-URL: documentation, https://ihcantabria.github.io/pyteseo
Project-URL: home, https://ihcantabria.com/specialized-software/english-teseo/
Project-URL: repository, https://github.com/IHCantabria/pyteseo
Provides-Extra: dev
